atta_jupyterlab-3.4.3.data/data/etc/jupyter/jupyter_notebook_config.d/jupyterlab.json
atta_jupyterlab-3.4.3.data/data/etc/jupyter/jupyter_server_config.d/jupyterlab.json
atta_jupyterlab-3.4.3.data/data/share/jupyter/lab/schemas/@jupyterlab/application-extension/commands.json
atta_jupyterlab-3.4.3.data/data/share/jupyter/lab/schemas/@jupyterlab/application-extension/context-menu.json
atta_jupyterlab-3.4.3.data/data/share/jupyter/lab/schemas/@jupyterlab/application-extension/package.json.orig
atta_jupyterlab-3.4.3.data/data/share/jupyter/lab/schemas/@jupyterlab/application-extension/shell.json
atta_jupyterlab-3.4.3.data/data/share/jupyter/lab/schemas/@jupyterlab/application-extension/sidebar.json
atta_jupyterlab-3.4.3.data/data/share/jupyter/lab/schemas/@jupyterlab/apputils-extension/package.json.orig
atta_jupyterlab-3.4.3.data/data/share/jupyter/lab/schemas/@jupyterlab/apputils-extension/palette.json
atta_jupyterlab-3.4.3.data/data/share/jupyter/lab/schemas/@jupyterlab/apputils-extension/print.json
atta_jupyterlab-3.4.3.data/data/share/jupyter/lab/schemas/@jupyterlab/apputils-extension/themes.json
atta_jupyterlab-3.4.3.data/data/share/jupyter/lab/schemas/@jupyterlab/apputils-extension/workspaces.json
atta_jupyterlab-3.4.3.data/data/share/jupyter/lab/schemas/@jupyterlab/cell-toolbar-extension/package.json.orig
atta_jupyterlab-3.4.3.data/data/share/jupyter/lab/schemas/@jupyterlab/cell-toolbar-extension/plugin.json
atta_jupyterlab-3.4.3.data/data/share/jupyter/lab/schemas/@jupyterlab/codemirror-extension/commands.json
atta_jupyterlab-3.4.3.data/data/share/jupyter/lab/schemas/@jupyterlab/codemirror-extension/package.json.orig
atta_jupyterlab-3.4.3.data/data/share/jupyter/lab/schemas/@jupyterlab/completer-extension/consoles.json
atta_jupyterlab-3.4.3.data/data/share/jupyter/lab/schemas/@jupyterlab/completer-extension/files.json
atta_jupyterlab-3.4.3.data/data/share/jupyter/lab/schemas/@jupyterlab/completer-extension/notebooks.json
atta_jupyterlab-3.4.3.dist-info/LICENSE
atta_jupyterlab-3.4.3.dist-info/METADATA
atta_jupyterlab-3.4.3.dist-info/WHEEL
atta_jupyterlab-3.4.3.dist-info/entry_points.txt
atta_jupyterlab-3.4.3.dist-info/top_level.txt
atta_jupyterlab-3.4.3.dist-info/RECORD
